{
  "author": "Sartaj.Sahota@sage.com",
  "approver": "Sartaj.Sahota@sage.com",
  "attributeSetName": "Product Information",
  "attributes": [
    {
      "name": "Tier",
      "values": [
        "Lite",
        "Lite50",
        "NW",
        "Prem",
        "SFA50",
        "SU"
      ]
    },
    {
      "name": "Version",
      "values": [
        "2026-0"
      ]
    },
    {
      "name": "Modules",
      "values": [
        "CIP",
        "Depr",
        "Track"
      ]
    }
  ],
  "categoryCode": "custom",
  "collections": [
    "custom_ca_customercare",
    "custom_us_customercare",
    "custom_ca_onehundred",
    "custom_ca_onehundred_contractor",
    "custom_us_onehundred_contractor",
    "custom_us_onehundred",
    "custom_au_en_threehundredcre",
    "custom_ca_threehundred_construction",
    "custom_us_threehundred_construction",
    "custom_ca_fifty",
    "custom_us_fifty",
    "custom_us_businessworks",
    "custom_ca_constructionmanagement",
    "custom_us_constructionmanagement",
    "custom_ca_fixedassets",
    "custom_us_fixedassets",
    "custom_us_timeslips",
    "custom_us_fiftyhosted"
  ],
  "createDate": 1733180807000,
  "diagnosticResponses": [],
  "fields": [
    {
      "name": "Description",
      "content": "<h3>What is Sage Expert Services (SES)?</h3> <p>Sage Expert Services (SES) provides advanced technical support through senior consultants and analysts for Sage customers and partners. We deliver value with competitively priced services tailored to your business needs. SES gives you access to trusted experts in Sage products and data. We're committed to supporting you so that your business can thrive. Check the service offerings for your product and schedule a free consultation today.</p> <h5><a href=\"#\" data-toggle=\"collapse\" data-target=\"#ec-1739211548221\"><span>▼SES service matrix&nbsp;</span></a></h5> <div id=\"ec-1739211548221\" class=\"collapse\" style=\"height: auto;\"> <table style=\"border-collapse: collapse; width: 99.8454%; height: 281px;\" border=\"1\"> <tbody> <tr style=\"height: 42px;\"> <td style=\"width: 12.4903%; text-align: center; vertical-align: middle; height: 42px;\">Service</td> <td style=\"width: 11%; text-align: center; vertical-align: middle; height: 42px;\"><strong>Sage 50</strong></td> <td style=\"width: 10%; text-align: center; vertical-align: middle; height: 42px;\"><strong>Sage 100</strong></td> <td style=\"width: 11%; text-align: center; vertical-align: middle; height: 42px;\"><strong>Sage 100 Contractor</strong></td> <td style=\"width: 11%; text-align: center; vertical-align: middle; height: 42px;\"><strong>Sage 300 CRE</strong></td> <td style=\"width: 11%; text-align: center; vertical-align: middle; height: 42px;\"><strong>Sage Fixed Assets</strong></td> <td style=\"width: 11%; text-align: center; vertical-align: middle; height: 42px;\"><strong>Sage Construction Management</strong></td> <td style=\"width: 11%; text-align: center; vertical-align: middle; height: 42px;\"><strong>Sage Timeslips</strong></td> </tr> <tr style=\"height: 21px;\"> <td style=\"width: 12.4903%; vertical-align: middle; text-align: left; height: 31px;\"> <p>Add-on Solutions</p> </td> <td style=\"width: 11%; text-align: center; vertical-align: middle; height: 31px;\">&nbsp;</td> <td style=\"width: 10%; text-align: center; vertical-align: middle; height: 31px;\">&nbsp;</td> <td style=\"width: 11%; text-align: center; vertical-align: middle; height: 31px;\">&nbsp;</td> <td style=\"width: 11%; text-align: center; vertical-align: middle; height: 31px;\">&nbsp;</td> <td style=\"width: 11%; text-align: center; vertical-align: middle; height: 31px;\"><span style=\"font-size: 11.0pt; line-height: 115%; font-family: 'Segoe UI Symbol',sans-serif;\">✔</span></td> <td style=\"width: 11%; text-align: center; vertical-align: middle; height: 31px;\">&nbsp;</td> <td style=\"width: 11%; text-align: center; vertical-align: middle; height: 31px;\">&nbsp;</td> </tr> <tr style=\"height: 21px;\"> <td style=\"width: 12.4903%; height: 21px; text-align: left; vertical-align: middle;\"> <p>Custom Reports</p> </td> <td style=\"width: 11%; text-align: center; vertical-align: middle; height: 19px;\"><span style=\"font-size: 11.0pt; line-height: 115%; font-family: 'Segoe UI Symbol',sans-serif;\">✔</span></td> <td style=\"width: 10%; text-align: center; vertical-align: middle; height: 19px;\"><span style=\"font-size: 11.0pt; line-height: 115%; font-family: 'Segoe UI Symbol',sans-serif;\">✔</span></td> <td style=\"width: 11%; text-align: center; vertical-align: middle; height: 19px;\">&nbsp;</td> <td style=\"width: 11%; text-align: center; vertical-align: middle; height: 19px;\"><span style=\"font-size: 11.0pt; line-height: 115%; font-family: 'Segoe UI Symbol',sans-serif;\">✔</span></td> <td style=\"width: 11%; text-align: center; vertical-align: middle; height: 19px;\">&nbsp;</td> <td style=\"width: 11%; text-align: center; vertical-align: middle; height: 19px;\"><span style=\"font-size: 11.0pt; line-height: 115%; font-family: 'Segoe UI Symbol',sans-serif;\">✔</span></td> <td style=\"width: 11%; text-align: center; vertical-align: middle; height: 19px;\"><span style=\"font-size: 11.0pt; line-height: 115%; font-family: 'Segoe UI Symbol',sans-serif;\">✔</span></td> </tr> <tr style=\"height: 21px;\"> <td style=\"width: 12.4903%; height: 19px; text-align: left; vertical-align: middle;\"> <p>Data management</p> </td> <td style=\"width: 11%; text-align: center; vertical-align: middle; height: 21px;\"><span style=\"font-size: 11.0pt; line-height: 115%; font-family: 'Segoe UI Symbol',sans-serif;\">✔</span></td> <td style=\"width: 10%; text-align: center; vertical-align: middle; height: 21px;\"><span style=\"font-size: 11.0pt; line-height: 115%; font-family: 'Segoe UI Symbol',sans-serif;\">✔</span></td> <td style=\"width: 11%; text-align: center; vertical-align: middle; height: 21px;\"><span style=\"font-size: 11.0pt; line-height: 115%; font-family: 'Segoe UI Symbol',sans-serif;\">✔</span></td> <td style=\"width: 11%; text-align: center; vertical-align: middle; height: 21px;\"><span style=\"font-size: 11.0pt; line-height: 115%; font-family: 'Segoe UI Symbol',sans-serif;\">✔</span></td> <td style=\"width: 11%; text-align: center; vertical-align: middle; height: 21px;\"><span style=\"font-size: 11.0pt; line-height: 115%; font-family: 'Segoe UI Symbol',sans-serif;\">✔</span></td> <td style=\"width: 11%; text-align: center; vertical-align: middle; height: 21px;\">&nbsp;</td> <td style=\"width: 11%; text-align: center; vertical-align: middle; height: 21px;\"><span style=\"font-size: 11.0pt; line-height: 115%; font-family: 'Segoe UI Symbol',sans-serif;\">✔</span></td> </tr> <tr style=\"height: 21px;\"> <td style=\"width: 12.4903%; vertical-align: middle; text-align: left; height: 21px;\"> <p>General Consulting</p> </td> <td style=\"width: 11%; text-align: center; vertical-align: middle; height: 21px;\">&nbsp;</td> <td style=\"width: 10%; text-align: center; vertical-align: middle; height: 21px;\"><span style=\"font-size: 11.0pt; line-height: 115%; font-family: 'Segoe UI Symbol',sans-serif;\">✔</span></td> <td style=\"width: 11%; text-align: center; vertical-align: middle; height: 21px;\">&nbsp;</td> <td style=\"width: 11%; text-align: center; vertical-align: middle; height: 21px;\"><span style=\"font-size: 11.0pt; line-height: 115%; font-family: 'Segoe UI Symbol',sans-serif;\">✔</span></td> <td style=\"width: 11%; text-align: center; vertical-align: middle; height: 21px;\">&nbsp;</td> <td style=\"width: 11%; text-align: center; vertical-align: middle; height: 21px;\"><span style=\"font-size: 11.0pt; line-height: 115%; font-family: 'Segoe UI Symbol',sans-serif;\">✔</span></td> <td style=\"width: 11%; text-align: center; vertical-align: middle; height: 21px;\">&nbsp;</td> </tr> <tr style=\"height: 21px;\"> <td style=\"width: 12.4903%; vertical-align: middle; text-align: left; height: 21px;\"> <p>Implementation</p> </td> <td style=\"width: 11%; text-align: center; vertical-align: middle; height: 21px;\">&nbsp;</td> <td style=\"width: 10%; text-align: center; vertical-align: middle; height: 21px;\"><span style=\"font-size: 11.0pt; line-height: 115%; font-family: 'Segoe UI Symbol',sans-serif;\">✔</span></td> <td style=\"width: 11%; text-align: center; vertical-align: middle; height: 21px;\">&nbsp;</td> <td style=\"width: 11%; text-align: center; vertical-align: middle; height: 21px;\">&nbsp;</td> <td style=\"width: 11%; text-align: center; vertical-align: middle; height: 21px;\">&nbsp;</td> <td style=\"width: 11%; text-align: center; vertical-align: middle; height: 21px;\"><span style=\"font-size: 11.0pt; line-height: 115%; font-family: 'Segoe UI Symbol',sans-serif;\">✔</span></td> <td style=\"width: 11%; text-align: center; vertical-align: middle; height: 21px;\">&nbsp;</td> </tr> <tr style=\"height: 21px;\"> <td style=\"width: 12.4903%; vertical-align: middle; text-align: left; height: 21px;\"> <p>Installation</p> </td> <td style=\"width: 11%; text-align: center; vertical-align: middle; height: 21px;\"><span style=\"font-size: 11.0pt; line-height: 115%; font-family: 'Segoe UI Symbol',sans-serif;\">✔</span></td> <td style=\"width: 10%; text-align: center; vertical-align: middle; height: 21px;\"><span style=\"font-size: 11.0pt; line-height: 115%; font-family: 'Segoe UI Symbol',sans-serif;\">✔</span></td> <td style=\"width: 11%; text-align: center; vertical-align: middle; height: 21px;\"><span style=\"font-size: 11.0pt; line-height: 115%; font-family: 'Segoe UI Symbol',sans-serif;\">✔</span></td> <td style=\"width: 11%; text-align: center; vertical-align: middle; height: 21px;\"><span style=\"font-size: 11.0pt; line-height: 115%; font-family: 'Segoe UI Symbol',sans-serif;\">✔</span></td> <td style=\"width: 11%; text-align: center; vertical-align: middle; height: 21px;\"><span style=\"font-size: 11.0pt; line-height: 115%; font-family: 'Segoe UI Symbol',sans-serif;\">✔</span></td> <td style=\"width: 11%; text-align: center; vertical-align: middle; height: 21px;\">&nbsp;</td> <td style=\"width: 11%; text-align: center; vertical-align: middle; height: 21px;\"><span style=\"font-size: 11.0pt; line-height: 115%; font-family: 'Segoe UI Symbol',sans-serif;\">✔</span></td> </tr> <tr style=\"height: 21px;\"> <td style=\"width: 12.4903%; vertical-align: middle; text-align: left; height: 21px;\"> <p>Migration</p> </td> <td style=\"width: 11%; text-align: center; vertical-align: middle; height: 21px;\"><span style=\"font-size: 11.0pt; line-height: 115%; font-family: 'Segoe UI Symbol',sans-serif;\">✔</span></td> <td style=\"width: 10%; text-align: center; vertical-align: middle; height: 21px;\"><span style=\"font-size: 11.0pt; line-height: 115%; font-family: 'Segoe UI Symbol',sans-serif;\">✔</span></td> <td style=\"width: 11%; text-align: center; vertical-align: middle; height: 21px;\"><span style=\"font-size: 11.0pt; line-height: 115%; font-family: 'Segoe UI Symbol',sans-serif;\">✔</span></td> <td style=\"width: 11%; text-align: center; vertical-align: middle; height: 21px;\"><span style=\"font-size: 11.0pt; line-height: 115%; font-family: 'Segoe UI Symbol',sans-serif;\">✔</span></td> <td style=\"width: 11%; text-align: center; vertical-align: middle; height: 21px;\"><span style=\"font-size: 11.0pt; line-height: 115%; font-family: 'Segoe UI Symbol',sans-serif;\">✔</span></td> <td style=\"width: 11%; text-align: center; vertical-align: middle; height: 21px;\">&nbsp;</td> <td style=\"width: 11%; text-align: center; vertical-align: middle; height: 21px;\"><span style=\"font-size: 11.0pt; line-height: 115%; font-family: 'Segoe UI Symbol',sans-serif;\">✔</span></td> </tr> <tr style=\"height: 21px;\"> <td style=\"width: 12.4903%; vertical-align: middle; text-align: left; height: 21px;\"> <p>Password Reset</p> </td> <td style=\"width: 11%; text-align: center; vertical-align: middle; height: 21px;\"><span style=\"font-size: 11.0pt; line-height: 115%; font-family: 'Segoe UI Symbol',sans-serif;\">✔</span></td> <td style=\"width: 10%; text-align: center; vertical-align: middle; height: 21px;\">&nbsp;</td> <td style=\"width: 11%; text-align: center; vertical-align: middle; height: 21px;\">&nbsp;</td> <td style=\"width: 11%; text-align: center; vertical-align: middle; height: 21px;\">&nbsp;</td> <td style=\"width: 11%; text-align: center; vertical-align: middle; height: 21px;\">&nbsp;</td> <td style=\"width: 11%; text-align: center; vertical-align: middle; height: 21px;\">&nbsp;</td> <td style=\"width: 11%; text-align: center; vertical-align: middle; height: 21px;\">&nbsp;</td> </tr> <tr style=\"height: 21px;\"> <td style=\"width: 12.4903%; vertical-align: middle; text-align: left; height: 21px;\"> <p>Upgrades</p> </td> <td style=\"width: 11%; text-align: center; vertical-align: middle; height: 21px;\"><span style=\"font-size: 11.0pt; line-height: 115%; font-family: 'Segoe UI Symbol',sans-serif;\">✔</span></td> <td style=\"width: 10%; text-align: center; vertical-align: middle; height: 21px;\"><span style=\"font-size: 11.0pt; line-height: 115%; font-family: 'Segoe UI Symbol',sans-serif;\">✔</span></td> <td style=\"width: 11%; text-align: center; vertical-align: middle; height: 21px;\"><span style=\"font-size: 11.0pt; line-height: 115%; font-family: 'Segoe UI Symbol',sans-serif;\">✔</span></td> <td style=\"width: 11%; text-align: center; vertical-align: middle; height: 21px;\"><span style=\"font-size: 11.0pt; line-height: 115%; font-family: 'Segoe UI Symbol',sans-serif;\">✔</span></td> <td style=\"width: 11%; text-align: center; vertical-align: middle; height: 21px;\"><span style=\"font-size: 11.0pt; line-height: 115%; font-family: 'Segoe UI Symbol',sans-serif;\">✔</span></td> <td style=\"width: 11%; text-align: center; vertical-align: middle; height: 21px;\">&nbsp;</td> <td style=\"width: 11%; text-align: center; vertical-align: middle; height: 21px;\">&nbsp;</td> </tr> <tr style=\"height: 21px;\"> <td style=\"width: 12.4903%; vertical-align: middle; text-align: left; height: 21px;\"> <p>Year-End Services</p> </td> <td style=\"width: 11%; text-align: center; vertical-align: middle; height: 21px;\"><span style=\"font-size: 11.0pt; line-height: 115%; font-family: 'Segoe UI Symbol',sans-serif;\">✔</span></td> <td style=\"width: 10%; text-align: center; vertical-align: middle; height: 21px;\"><span style=\"font-size: 11.0pt; line-height: 115%; font-family: 'Segoe UI Symbol',sans-serif;\">✔</span></td> <td style=\"width: 11%; text-align: center; vertical-align: middle; height: 21px;\"><span style=\"font-size: 11.0pt; line-height: 115%; font-family: 'Segoe UI Symbol',sans-serif;\">✔</span></td> <td style=\"width: 11%; text-align: center; vertical-align: middle; height: 21px;\"><span style=\"font-size: 11.0pt; line-height: 115%; font-family: 'Segoe UI Symbol',sans-serif;\">✔</span></td> <td style=\"width: 11%; text-align: center; vertical-align: middle; height: 21px;\">&nbsp;</td> <td style=\"width: 11%; text-align: center; vertical-align: middle; height: 21px;\">&nbsp;</td> <td style=\"width: 11%; text-align: center; vertical-align: middle; height: 21px;\">&nbsp;</td> </tr> </tbody> </table> <p>&nbsp;</p> </div> <h4 id=\"dl-sesservicematrix1292\" class=\"expand-collapse\"></h4> <h3>Service details by product</h3> <div id=\"ec-1738968190037\" class=\"collapse in\" style=\"height: auto;\"></div> <h5 class=\"expand-collapse\"><a href=\"#\" data-toggle=\"collapse\" data-target=\"#ec-1738968837703\"><em class=\"icon-arrow-up\"></em><em class=\"icon-arrow-down\"></em><span>▼ Sage 50</span></a></h5> <div id=\"ec-1738968837703\" class=\"collapse\" style=\"height: auto;\"> <ul> <li><strong>Custom Reports:</strong> Design and creation of custom reports and financial statements.</li> <li><strong>Customization</strong>: <span style=\"letter-spacing: 0.2px;\">Logicim XLGL Advanced Reports, Forms (AR, AP, and Payroll).</span></li> <li><strong>Data Conversion:</strong> Data conversions from old versions.</li> <li><strong>Data Migration:</strong> Data migrations from other accounting products – Lists and Balances Only.</li> <li><strong>Data Rebuild:</strong> Lists and Balances ONLY rebuild to change accounting method or fiscal year.</li> <li><strong>Install Onboarding:</strong> Step-by-step walk-through of Sage 50 installation.</li> <li><strong>Payroll Formula Service:</strong> User-maintained formula creation (Limited to documented Sage Payroll formulas).</li> <li><strong>Year-End Services:</strong> Step-by-step walk-through of the year-end process.</li> <li><strong>Password reset:</strong> Resetting the password for unsupported versions of Sage 50 only.</li> </ul> </div> <h5 class=\"expand-collapse\"><a href=\"#\" data-toggle=\"collapse\" data-target=\"#ec-1738969812652\"><em class=\"icon-arrow-up\"></em><em class=\"icon-arrow-down\"></em><span>▼ Sage 100</span></a></h5> <div id=\"ec-1738969812652\" class=\"collapse\" style=\"height: auto;\"> <ul> <li><strong>Business Process Review: </strong>Customer business process review with analysis needs.</li> <li><strong>Custom Reports:</strong> Design and creation of custom reports.</li> <li><strong>Customizations:</strong> Design and create Custom Office Customizer User-Defined Tables, fields and processes.</li> <li><strong>Database Upgrades: </strong>Provide MAS 90/200, Sage 100 software installation, and database upgrades to the latest release version.</li> <li><strong>Full Implementations:</strong> Perform full implementations on behalf of the partner.</li> <li><strong>General Consulting:</strong> Provide general product consultation.</li> <li><strong>Partner-Assisted Implementations:</strong> Assist partner in new Sage 100ERP implementations, including database migrations.</li> <li><strong>Product Updates and Fixes:</strong> Installation of the same version of product updates and product fixes.</li> <li><strong>Sage Partner Portal Migrations:</strong> Assist partners in transitioning customers' on-premise databases to Sage partner-hosted site.</li> <li><strong>Training:</strong> Customer-defined comprehensive training for Sage 100.</li> <li><strong>Visual Integrator Jobs:</strong> Design and creation of custom import/export jobs.</li> <li><strong>Installation:</strong> Sage 100 installation and registration, including basic user setup.</li> <li><strong>Year-End Services:</strong> Step-by-step walk-through of the year-end process and 1099 and W2 processing.</li> </ul> </div> <h5 class=\"expand-collapse\"><a href=\"#\" data-toggle=\"collapse\" data-target=\"#ec-1738970176397\"><em class=\"icon-arrow-up\"></em><em class=\"icon-arrow-down\"></em><span>▼ Sage 100 Contractor</span></a></h5> <div id=\"ec-1738970176397\" class=\"collapse\" style=\"height: auto;\"> <ul> <li><strong>Data Services: </strong>File fixes and fiscal year-end change.</li> <li><strong>General Consulting: </strong>We don’t offer general consultation.</li> <li><strong>Installation: </strong>New Installation with sample data.</li> <li><strong>Server Migration:</strong> Migrating a Sage 100 Contractor server to a new environment.</li> <li><strong>Upgrade Services:</strong> Upgrading to the latest version.</li> </ul> </div> <h5 id=\"dl-sage100contractor1237\" class=\"expand-collapse\"></h5> <h5 class=\"expand-collapse\"><a href=\"#\" data-toggle=\"collapse\" data-target=\"#ec-1738973100345\"><em class=\"icon-arrow-up\"></em><em class=\"icon-arrow-down\"></em><span>▼ Sage 300 CRE</span></a></h5> <div id=\"ec-1738973100345\" class=\"collapse\" style=\"height: auto;\"> <ul> <li><strong>Custom Reports: </strong>Design, create, and test custom reporting requirements for using Report Designer or Crystal Reports.</li> <li><strong>Data Merge: </strong>A data merge is the process of consolidating multiple data folders into one. <span>Storing all data in a single folder is now more feasible and easier than using separate folders. </span>Most data merges also require key changes.</li> <li><strong>Data Modifications: </strong>Data modifications when it's not possible or practical to edit data directly in the program. <ul> <li>Updating multiple employees pay information</li> <li>Adding the bank ID to many AP distributions</li> <li>Changing the GL retrieval method in Job Cost</li> <li>Removing unwanted data</li> <li>Changing GL periods or fiscal end dates, etc.</li> </ul> </li> <li><strong>Data Splits:</strong> <span>When you need to separate multiple companies' data in a folder, we can perform data splits. </span>This occurs when you sell a company, or the customer must control user access by the company. SES can help facilitate this by splitting a single database into multiple new databases.</li> <li><strong>General Consulting: </strong>SES offers general product advisory services.</li> <li><strong>Installation and upgrade: </strong>Installation and upgrade of Sage 300 CRE on servers and workstations.</li> <li><strong>Key Changes: </strong>This process finds and replaces key fields based on the spreadsheet or the provided criteria. Companies often outgrow their setup and require a key change to maintain the software's optimal performance.</li> <li><strong>Server Migration:</strong> Migrating the server and data to a new location.</li> </ul> </div> <h4 id=\"dl-sage300cre1791\" class=\"expand-collapse\"></h4> <h5 class=\"expand-collapse\"><a href=\"#\" data-toggle=\"collapse\" data-target=\"#ec-1738973160890\"><em class=\"icon-arrow-up\"></em><em class=\"icon-arrow-down\"></em><span>▼ Sage Fixed Assets</span></a></h5> <div id=\"ec-1738973160890\" class=\"collapse\" style=\"height: auto;\"> <ul> <li><strong>Add-on Solutions: </strong>Sage Expert Services can deliver applications that expand on the functionality of the core Sage Fixed Assets software. <ul> <li><strong>Advanced Import Utility</strong> <strong>for Depreciation</strong>&nbsp;importing data that integrates with ERP source data</li> <li><strong>Advanced Import utility for Planning</strong> integrates with ERP source data</li> <li><strong>Global Security Manager</strong> allows users to manage security across multiple companies from a single interface</li> <li><strong>Posting Link</strong> outputs GL files in a customer-specified format for depreciation, additions, and disposals</li> </ul> </li> <li><strong>Data Conversion:</strong> Convert and import data from third-party applications into Sage Fixed Assets or Sage Planning. Data formatting and validation in Sage Fixed Assets. Identify potential data issues before importing and present options for resolving the issues. The cost depends on the number of companies, assets, and data complexity.</li> <li><strong>Data File Maintenance:</strong> Edit existing data in the Sage Fixed Assets application. For example, revalue assets due to an acquisition. The fee varies with company size, number of assets, and edits required.</li> <li><strong>Database Rebuilds and Recovery:</strong> Rebuild a database using various tools to correct data corruption.</li> <li><strong>Database Upgrade:</strong> Upgrading an existing database to the most current version.</li> <li><strong>Installation:</strong> Sage will install the application remotely. The installation includes both the server and client components. We perform installations in both on-premise and hosted environments. The installation services include up to five client machines. Extra charges can apply for more client installations.</li> <li><strong>Managed Services:</strong> Sage handles all product updates and patches for a customer. Sage will contact the customer to schedule the update when a new release is available.</li> </ul> </div> <h5 id=\"dl-sagefixedassets1995\" class=\"expand-collapse\"></h5> <h5 class=\"expand-collapse\"><a href=\"#\" data-toggle=\"collapse\" data-target=\"#ec-1738973206354\"><em class=\"icon-arrow-up\"></em><em class=\"icon-arrow-down\"></em><span>▼ Sage Construction Management</span></a></h5> <div id=\"ec-1738973206354\" class=\"collapse\" style=\"height: auto;\"> <ul> <li><strong>Implementations:</strong> Implementation and configuration – All modules.</li> <li><strong>Custom Reports:</strong> Design and creation of custom reports.</li> <li><strong>General Consulting: </strong>Provide general product advisory.</li> </ul> </div> <h4 id=\"dl-sageconstructionmanagement1696\" class=\"expand-collapse\"></h4> <h5 class=\"expand-collapse\"><a href=\"#\" data-toggle=\"collapse\" data-target=\"#ec-1738973254386\"><em class=\"icon-arrow-up\"></em><em class=\"icon-arrow-down\"></em><span>▼ Sage Timeslips</span></a></h5> <div id=\"ec-1738973254386\" class=\"collapse\" style=\"height: auto;\"> <ul> <li><strong>Customizations:</strong> Form and report customizations.</li> <li><strong>Data Conversion:</strong> Convert data from prior versions of Timeslips.</li> <li><strong>Data Migration:</strong> Migrate data from third-party applications.</li> <li><strong>Installation:</strong> Step-by-step installation in the customer environment.</li> </ul> </div> <h4 id=\"dl-sagetimeslips1078\" class=\"expand-collapse\"></h4> <p><span class=\"ra-content-note-1 mceNonEditable\" style=\"color: #468847;\"><span><img class=\"ra-att-img\" src=\"https://internal-kb.sage.com/portal/app/images/content_note.gif\" alt=\"\" width=\"18px\" height=\"17px\">&nbsp;<strong class=\"ra-att-title\">NOTE:</strong>&nbsp;</span><span class=\"ra-att-desc mceEditable\">Sage experts perform all the work by remotely connecting to the customer's environment. The fee varies based on the number of PCs, databases, and data and environment complexity </span></span>&nbsp;</p> <h3>Key SES advantages</h3> <ul> <li>We only charge fees after confirming that we can meet your needs.</li> <li>A dedicated expert will guide you through the entire support process.</li> <li>We work with your schedule to minimize disruptions to your business.</li> </ul> <h3>How do I contact SES?</h3> <p><a rel=\"noopener\" href=\"https://forms.office.com/r/DcaMpWASCE\" target=\"_blank\"><strong>Fill in the form describing your needs</strong></a><strong><a rel=\"noopener\" href=\"https://forms.office.com/r/DcaMpWASCE\" target=\"_blank\"></a></strong>, and we'll contact you within two business days.</p>"
    }
  ],
  "id": "241202230647740",
  "language": "English",
  "lastModifiedDate": 1746200370000,
  "minorModifiedDate": 1752163088000,
  "keywords": "SES Sage-expert-service expert-services",
  "question": null,
  "renewDate": 1890864000000,
  "solutionBoost": 1.0,
  "status": "Published",
  "type": "Template Solution",
  "taxonomy": [
    "Category//Installation"
  ],
  "templateName": "5 - Customer Care",
  "title": "Sage Expert Services (SES)",
  "translations": [],
  "viewCount": 6830,
  "solvedCount": 196,
  "unsolvedCount": 18,
  "summary": "What does Sage Expert Services (SES) offer, and how do I contact them?",
  "revisionID": null,
  "templateSolutionID": "PRE63029"
}